whirlpool/__init__.py
whirlpool/aircon.py
whirlpool/appliance.py
whirlpool/appliancesmanager.py
whirlpool/auth.py
whirlpool/backendselector.py
whirlpool/dryer.py
whirlpool/eventsocket.py
whirlpool/oven.py
whirlpool/refrigerator.py
whirlpool/types.py
whirlpool/washer.py
whirlpool_sixth_sense-1.1.0.dist-info/licenses/LICENSE
whirlpool_sixth_sense-1.1.0.dist-info/METADATA
whirlpool_sixth_sense-1.1.0.dist-info/WHEEL
whirlpool_sixth_sense-1.1.0.dist-info/top_level.txt
whirlpool_sixth_sense-1.1.0.dist-info/RECORD
