Metadata-Version: 2.4
Name: whirlpool_sixth_sense
Version: 1.1.0
Summary: Unofficial API for Whirlpool's 6th Sense appliances
Author-email: Abílio Costa <amfcalt@gmail.com>
License-Expression: MIT
Project-URL: Homepage, https://github.com/abmantis/whirlpool-sixth-sense/
Classifier: Programming Language :: Python :: 3
Classifier: Operating System :: OS Independent
Requires-Python: >=3.11
License-File: LICENSE
Requires-Dist: aiohttp>=3.9.1
Requires-Dist: websockets>=8.1
Requires-Dist: async-timeout>=4.0.3
Dynamic: license-file
